tlscan/__init__.py
tlscan/__main__.py
tlscan/ASN1/DER.py
tlscan/ASN1/__init__.py
tlscan/ASN1/constants.py
tlscan/ASN1/x509.py
tlscan/TLS/__init__.py
tlscan/TLS/ciphers.py
tlscan/TLS/constants.py
tlscan/TLS/extensions.py
tlscan/TLS/protocols.py
tlscan/TLS/tcp.py
tlscan/TLS/tlsconnection.py
tlscan/TLS/tlsrecord.py
tlscan/scanner/__init__.py
tlscan/scanner/enumerator.py
tlscan/scanner/target.py
tlscan-0.0.3.dist-info/LICENSE.txt
tlscan-0.0.3.dist-info/METADATA
tlscan-0.0.3.dist-info/WHEEL
tlscan-0.0.3.dist-info/entry_points.txt
tlscan-0.0.3.dist-info/top_level.txt
tlscan-0.0.3.dist-info/RECORD
