Metadata-Version: 2.2
Name: tlscan
Version: 0.0.3
Summary: Python based TLS enumeration scanner
Author-email: "M.H. Jansen of Lorkeers" <marco@threatlabs.eu>
Maintainer-email: ThreatLabs <info@threatlabs.eu>
License: # The MIT License (MIT)
Project-URL: Homepage, https://github.com/ThreatLabsNL/TLScan
Project-URL: Bug Reports, https://github.com/ThreatLabsNL/TLScan/issues
Project-URL: Source, https://github.com/ThreatLabsNL/TLScan/
Keywords: tls,scanner,security
Classifier: Development Status :: 5 - Production/Stable
Classifier: Intended Audience :: Information Technology
Classifier: License :: OSI Approved :: MIT License
Classifier: Programming Language :: Python :: 3
Classifier: Programming Language :: Python :: 3.9
Classifier: Programming Language :: Python :: 3.10
Classifier: Programming Language :: Python :: 3.11
Classifier: Programming Language :: Python :: 3.12
Classifier: Programming Language :: Python :: 3.13
Classifier: Programming Language :: Python :: 3 :: Only
Requires-Python: >=3.9
License-File: LICENSE.txt
